temporal/__init__.py
temporal/activity.py
temporal/activity_loop.py
temporal/activity_method.py
temporal/async_activity.py
temporal/clock_decision_context.py
temporal/constants.py
temporal/conversions.py
temporal/converter.py
temporal/decision_loop.py
temporal/decisions.py
temporal/errors.py
temporal/exception_handling.py
temporal/exceptions.py
temporal/marker.py
temporal/replay_interceptor.py
temporal/retry.py
temporal/service_helpers.py
temporal/state_machines.py
temporal/util.py
temporal/worker.py
temporal/workerfactory.py
temporal/workflow.py
temporal/api/__init__.py
temporal/api/command/__init__.py
temporal/api/command/v1.py
temporal/api/common/__init__.py
temporal/api/common/v1.py
temporal/api/enums/__init__.py
temporal/api/enums/v1.py
temporal/api/errordetails/__init__.py
temporal/api/errordetails/v1.py
temporal/api/failure/__init__.py
temporal/api/failure/v1.py
temporal/api/filter/__init__.py
temporal/api/filter/v1.py
temporal/api/history/__init__.py
temporal/api/history/v1.py
temporal/api/namespace/__init__.py
temporal/api/namespace/v1.py
temporal/api/query/__init__.py
temporal/api/query/v1.py
temporal/api/replication/__init__.py
temporal/api/replication/v1.py
temporal/api/taskqueue/__init__.py
temporal/api/taskqueue/v1.py
temporal/api/version/__init__.py
temporal/api/version/v1.py
temporal/api/workflow/__init__.py
temporal/api/workflow/v1.py
temporal/api/workflowservice/__init__.py
temporal/api/workflowservice/v1.py
temporal_python_sdk-1.0.19.dist-info/LICENSE
temporal_python_sdk-1.0.19.dist-info/METADATA
temporal_python_sdk-1.0.19.dist-info/WHEEL
temporal_python_sdk-1.0.19.dist-info/top_level.txt
temporal_python_sdk-1.0.19.dist-info/RECORD
