Metadata-Version: 2.1
Name: temporal-python-sdk
Version: 1.0.19
Summary: Unofficial Python SDK for the Temporal Workflow Engine
Home-page: https://github.com/firdaus/temporal-python-sdk
Author: Mohammed Firdaus
Author-email: firdaus.halim@gmail.com
License: UNKNOWN
Platform: UNKNOWN
Classifier: Programming Language :: Python :: 3
Classifier: Programming Language :: Python :: 3.7
Classifier: Programming Language :: Python :: 3.8
Classifier: License :: OSI Approved :: MIT License
Classifier: Operating System :: OS Independent
Requires-Dist: betterproto-for-temporal-python-sdk (==1.2.5)
Requires-Dist: dataclasses-json (==0.3.8)
Requires-Dist: grpcio (==1.30.0)
Requires-Dist: grpclib (==0.3.2)
Requires-Dist: h2 (==3.2.0)
Requires-Dist: more-itertools (==7.0.0)
Requires-Dist: pytz (==2020.1)
Requires-Dist: tblib (==1.6.0)
